mzcst_2024/__init__.py
mzcst_2024/_global.py
mzcst_2024/common.py
mzcst_2024/component.py
mzcst_2024/construction_curve.py
mzcst_2024/construction_face.py
mzcst_2024/curves.py
mzcst_2024/group.py
mzcst_2024/interface.py
mzcst_2024/material.py
mzcst_2024/math_.py
mzcst_2024/modeling.py
mzcst_2024/plot.py
mzcst_2024/profiles_to_shapes.py
mzcst_2024/results.py
mzcst_2024/shape_operations.py
mzcst_2024/shapes.py
mzcst_2024/transformations_and_picks.py
mzcst_2024/units.py
mzcst_2024/asymptotic/__init__.py
mzcst_2024/asymptotic/raydata.py
mzcst_2024/eda/__init__.py
mzcst_2024/eda/geometry2d.py
mzcst_2024/eda/part_library.py
mzcst_2024/eda/pcb_api.py
mzcst_2024/monitors/__init__.py
mzcst_2024/radar/__init__.py
mzcst_2024/radar/channel_tensor.py
mzcst_2024/radar/coordinate_systems.py
mzcst_2024/radar/plot.py
mzcst_2024/radar/range_.py
mzcst_2024/radar/range_angle.py
mzcst_2024/radar/spectral_algorithms.py
mzcst_2024/solver/__init__.py
mzcst_2024/solver/_general.py
mzcst_2024/solver/hf.py
mzcst_2024/solver/lf.py
mzcst_2024/solver/mechanics.py
mzcst_2024/solver/particles.py
mzcst_2024/solver/thermal.py
mzcst_2024/sources_and_ports/__init__.py
mzcst_2024/sources_and_ports/hf.py
mzcst_2024/utils/__init__.py
mzcst_2024/utils/surfaces.py
mzcst_2024-2025.12.15.dist-info/METADATA
mzcst_2024-2025.12.15.dist-info/WHEEL
mzcst_2024-2025.12.15.dist-info/licenses/LICENSE
mzcst_2024-2025.12.15.dist-info/RECORD
