Metadata-Version: 2.4
Name: mzcst_2024
Version: 2025.12.15
Summary: An interface for Python 3.10 and CST Studio Suite 2024. It may work on newer versions, but it is not guaranteed.
Project-URL: Homepage, https://github.com/PlasticLie/mzcst_2024
Project-URL: Issues, https://github.com/PlasticLie/mzcst_2024/issues
Author-email: Li Mengzi <limengzi96@outlook.com>
License-Expression: MIT
License-File: LICENSE
Classifier: Operating System :: Microsoft :: Windows
Classifier: Programming Language :: Python :: 3.10
Requires-Python: <=3.11,>=3.10
Requires-Dist: h5py>=3.6.0
Requires-Dist: matplotlib>=3.3.4
Requires-Dist: numpy>=1.21.4
Requires-Dist: scipy>=1.5.4
